{
  "weekday": {
    "Purple": { "first": "05:00", "last": "23:00",
      "headway": [
        {"from":"05:00","to":"06:00","mins":20},
        {"from":"06:00","to":"10:57","mins":10},
        {"from":"10:57","to":"15:21","mins":8},
        {"from":"15:21","to":"22:01","mins":10},
        {"from":"22:01","to":"23:00","mins":15}
      ]
    },
    "Green": { "first": "05:00", "last": "23:05",
      "headway": [
        {"from":"05:00","to":"06:15","mins":15},
        {"from":"06:15","to":"10:25","mins":10},
        {"from":"10:25","to":"15:51","mins":7},
        {"from":"15:51","to":"20:29","mins":10},
        {"from":"20:29","to":"22:57","mins":12}
      ]
    },
    "Yellow": { "first": "06:00", "last": "22:30",
      "headway": [
        {"from":"06:00","to":"10:00","mins":8},
        {"from":"10:00","to":"17:00","mins":10},
        {"from":"17:00","to":"21:00","mins":8},
        {"from":"21:00","to":"22:30","mins":12}
      ]
    }
  },
  "weekend": {
    "Purple": { "first": "06:00", "last": "22:30",
      "headway": [
        {"from":"06:00","to":"10:00","mins":10},
        {"from":"10:00","to":"18:00","mins":10},
        {"from":"18:00","to":"22:30","mins":12}
      ]
    },
    "Green": { "first": "06:00", "last": "22:30",
      "headway": [
        {"from":"06:00","to":"10:00","mins":10},
        {"from":"10:00","to":"18:00","mins":10},
        {"from":"18:00","to":"22:30","mins":12}
      ]
    },
    "Yellow": { "first": "06:30", "last": "22:00",
      "headway": [
        {"from":"06:30","to":"10:00","mins":10},
        {"from":"10:00","to":"18:00","mins":12},
        {"from":"18:00","to":"22:00","mins":12}
      ]
    }
  },
  "sunday": {
    "Purple": { "first": "06:00", "last": "22:00", "headway":[{"from":"06:00","to":"22:00","mins":10}] },
    "Green":  { "first": "06:00", "last": "22:00", "headway":[{"from":"06:00","to":"22:00","mins":10}] },
    "Yellow": { "first": "06:30", "last": "22:00", "headway":[{"from":"06:30","to":"22:00","mins":12}] }
  }
}
